odoo/addons/commission_formula_oca/README.rst
odoo/addons/commission_formula_oca/__init__.py
odoo/addons/commission_formula_oca/__manifest__.py
odoo/addons/commission_formula_oca/demo/commission_demo.xml
odoo/addons/commission_formula_oca/i18n/ca.po
odoo/addons/commission_formula_oca/i18n/commission_formula.pot
odoo/addons/commission_formula_oca/i18n/commission_formula_oca.pot
odoo/addons/commission_formula_oca/i18n/de.po
odoo/addons/commission_formula_oca/i18n/el_GR.po
odoo/addons/commission_formula_oca/i18n/es.po
odoo/addons/commission_formula_oca/i18n/es_AR.po
odoo/addons/commission_formula_oca/i18n/fi.po
odoo/addons/commission_formula_oca/i18n/fr.po
odoo/addons/commission_formula_oca/i18n/it.po
odoo/addons/commission_formula_oca/i18n/pt.po
odoo/addons/commission_formula_oca/i18n/pt_BR.po
odoo/addons/commission_formula_oca/i18n/pt_PT.po
odoo/addons/commission_formula_oca/i18n/ru.po
odoo/addons/commission_formula_oca/i18n/sale_commission_formula.pot
odoo/addons/commission_formula_oca/i18n/sl.po
odoo/addons/commission_formula_oca/i18n/tr.po
odoo/addons/commission_formula_oca/i18n/tr_TR.po
odoo/addons/commission_formula_oca/i18n/zh_CN.po
odoo/addons/commission_formula_oca/models/__init__.py
odoo/addons/commission_formula_oca/models/commission.py
odoo/addons/commission_formula_oca/models/commission_mixin.py
odoo/addons/commission_formula_oca/readme/CONTRIBUTORS.md
odoo/addons/commission_formula_oca/readme/DESCRIPTION.md
odoo/addons/commission_formula_oca/readme/USAGE.md
odoo/addons/commission_formula_oca/static/description/icon.png
odoo/addons/commission_formula_oca/static/description/icon.svg
odoo/addons/commission_formula_oca/static/description/index.html
odoo/addons/commission_formula_oca/static/src/css/commission_formula_oca.css
odoo/addons/commission_formula_oca/views/commission_view.xml
odoo_addon_commission_formula_oca-18.0.1.0.0.2.dist-info/METADATA
odoo_addon_commission_formula_oca-18.0.1.0.0.2.dist-info/WHEEL
odoo_addon_commission_formula_oca-18.0.1.0.0.2.dist-info/top_level.txt
odoo_addon_commission_formula_oca-18.0.1.0.0.2.dist-info/RECORD
