Metadata-Version: 2.1
Name: odoo-addon-commission_formula_oca
Version: 18.0.1.0.0.2
Requires-Python: >=3.10
Requires-Dist: odoo-addon-commission_oca==18.0.*
Requires-Dist: odoo==18.0.*
Summary: Commissions computed by formulas
Home-page: https://github.com/OCA/commission
License: AGPL-3
Author: Abstract,Odoo Community Association (OCA)
Author-email: support@odoo-community.org
Classifier: Programming Language :: Python
Classifier: Framework :: Odoo
Classifier: Framework :: Odoo :: 18.0
Classifier: License :: OSI Approved :: GNU Affero General Public License v3
